[
  {
    "title": "美 벌금에도 59조, 홍콩 단계적 허용…레버리지 연착륙 비결",
    "url": "https://www.joongang.co.kr/article/25446119",
    "date": "2026-07-19",
    "category": "경제",
    "source": "중앙일보",
    "scraped_at": "2026-07-19T09:44:33.340766+09:00",
    "main_category": "경제",
    "image_url": "https://pds.joongang.co.kr/news/component/htmlphoto_mmdata/202607/19/9bc66666-6fd4-4b33-8a3a-c406fd1d7ae7.jpg"
  },
  {
    "title": "재벌집 막내아들 홀로서기 시작…의좋은 한화 삼형제의 미래",
    "url": "https://www.joongang.co.kr/article/25446046",
    "date": "2026-07-19",
    "category": "경제",
    "source": "중앙일보",
    "scraped_at": "2026-07-19T09:44:33.340855+09:00",
    "main_category": "경제",
    "image_url": "https://pds.joongang.co.kr/news/FbMetaImage/202607/4814e496-38ee-4f57-99cd-f0f810dcc4b6.jpg"
  },
  {
    "title": "디자인 모르는 할머니, 극찬하며 사간 프라이팬 정체 [비크닉]",
    "url": "https://www.joongang.co.kr/article/25446087",
    "date": "2026-07-19",
    "category": "경제",
    "source": "중앙일보",
    "scraped_at": "2026-07-19T09:44:33.340948+09:00",
    "main_category": "경제",
    "image_url": "https://pds.joongang.co.kr/news/component/htmlphoto_mmdata/202607/18/73722802-964f-4fb3-9444-8f65c09fd5b7.jpg"
  },
  {
    "title": "“호남 반도체 투자가 협상 대상?” 삼전 노조에 분노한 주주들",
    "url": "https://www.joongang.co.kr/article/25446137",
    "date": "2026-07-19",
    "category": "경제",
    "source": "중앙일보",
    "scraped_at": "2026-07-19T09:44:33.341056+09:00",
    "main_category": "경제",
    "image_url": "https://pds.joongang.co.kr/news/component/htmlphoto_mmdata/202607/19/12a0ec28-26dd-4c2a-95cb-0934a64fb495.jpg"
  },
  {
    "title": "‘마운자로’ 다음은 환각제? 비만약 대박 신화 제약사의 승부수",
    "url": "https://www.joongang.co.kr/article/25446053",
    "date": "2026-07-19",
    "category": "경제",
    "source": "중앙일보",
    "scraped_at": "2026-07-19T09:44:33.341179+09:00",
    "main_category": "경제",
    "image_url": ""
  }
]