[
  {
    "title": "워커힐호텔, ‘명절 선물’ 판매로 사업 다각화… “소비자와 소통 확대”",
    "url": "https://www.donga.com/news/Culture/article/all/20260113/133149682/1",
    "date": "2026-01-13",
    "category": "문화",
    "source": "동아일보",
    "image_url": "https://dimg.donga.com/wps/NEWS/IMAGE/2026/01/13/133149668.2.jpg",
    "scraped_at": "2026-01-13T19:11:31.429788+09:00",
    "main_category": "문화"
  },
  {
    "title": "최진혁 “2026년에 아기 생긴다 했는데… 올해 편성된 것 운명”",
    "url": "https://www.donga.com/news/Culture/article/all/20260113/133146973/1",
    "date": "2026-01-13",
    "category": "문화",
    "source": "동아일보",
    "image_url": "https://dimg.donga.com/wps/NEWS/IMAGE/2026/01/13/133146964.1.jpg",
    "scraped_at": "2026-01-13T19:11:31.429882+09:00",
    "main_category": "문화"
  },
  {
    "title": "‘서울대 남편♥’ 효민, 파격 비주얼로 올린 근황 공개",
    "url": "https://www.donga.com/news/Culture/article/all/20260113/133148249/1",
    "date": "2026-01-13",
    "category": "문화",
    "source": "동아일보",
    "image_url": "https://dimg.donga.com/wps/NEWS/IMAGE/2026/01/13/133148250.1.jpg",
    "scraped_at": "2026-01-13T19:11:31.429949+09:00",
    "main_category": "문화"
  },
  {
    "title": "파리 호텔 감성 그대로…‘모노그램’ 130주년 기념 팝업 열어",
    "url": "https://www.donga.com/news/Culture/article/all/20260113/133147709/1",
    "date": "2026-01-13",
    "category": "문화",
    "source": "동아일보",
    "image_url": "https://dimg.donga.com/wps/NEWS/IMAGE/2026/01/13/133147735.1.jpg",
    "scraped_at": "2026-01-13T19:11:31.430016+09:00",
    "main_category": "문화"
  },
  {
    "title": "세계를 사로잡은 ‘이건희 컬렉션’…K컬처 품격 업그레이드",
    "url": "https://www.donga.com/news/Culture/article/all/20260113/133144625/1",
    "date": "2026-01-13",
    "category": "문화",
    "source": "동아일보",
    "image_url": "https://dimg.donga.com/wps/NEWS/IMAGE/2026/01/13/133144646.1.jpg",
    "scraped_at": "2026-01-13T19:11:31.430077+09:00",
    "main_category": "문화"
  }
]