[
  {
    "title": "문희준 “결혼 일찍 할 걸…나이 많아 셋째는 못 낳아”",
    "url": "https://www.donga.com/news/Culture/article/all/20260207/133316435/1",
    "date": "2026-02-07",
    "category": "문화",
    "source": "동아일보",
    "image_url": "https://dimg.donga.com/wps/NEWS/IMAGE/2026/02/07/133316436.1.jpg",
    "scraped_at": "2026-02-07T09:40:45.899960+09:00",
    "main_category": "문화"
  },
  {
    "title": "“불안이 덮칠 땐 내가 통제할 수 있는 것에 집중하라”[손효림의 글로벌 책터뷰]",
    "url": "https://www.donga.com/news/Culture/article/all/20260206/133314502/2",
    "date": "2026-02-06",
    "category": "문화",
    "source": "동아일보",
    "image_url": "https://dimg.donga.com/wps/NEWS/IMAGE/2026/02/06/133316100.1.jpg",
    "scraped_at": "2026-02-07T09:40:45.900042+09:00",
    "main_category": "문화"
  },
  {
    "title": "[오늘의 운세/2월 7일]",
    "url": "https://www.donga.com/news/Culture/article/all/20260206/133314518/2",
    "date": "2026-02-06",
    "category": "문화",
    "source": "동아일보",
    "image_url": "https://dimg.donga.com/wps/NEWS/IMAGE/2026/02/06/133316091.1.jpg",
    "scraped_at": "2026-02-07T09:40:45.900109+09:00",
    "main_category": "문화"
  },
  {
    "title": "[오늘의 운세/2월 8일]",
    "url": "https://www.donga.com/news/Culture/article/all/20260206/133314528/2",
    "date": "2026-02-06",
    "category": "문화",
    "source": "동아일보",
    "image_url": "https://dimg.donga.com/wps/NEWS/IMAGE/2026/02/06/133316074.1.jpg",
    "scraped_at": "2026-02-07T09:40:45.900179+09:00",
    "main_category": "문화"
  },
  {
    "title": "김이 모락모락 피어오르는 해수 온천 위로 떠오르는 태양[전승훈 기자의 아트로드]",
    "url": "https://www.donga.com/news/Culture/article/all/20260206/133314443/2",
    "date": "2026-02-06",
    "category": "문화",
    "source": "동아일보",
    "image_url": "https://dimg.donga.com/wps/NEWS/IMAGE/2026/02/06/133312868.4.jpg",
    "scraped_at": "2026-02-07T09:40:45.900245+09:00",
    "main_category": "문화"
  }
]