[
  {
    "title": "합천서 내리막에 미끌어진 경운기 깔린 70대 숨져",
    "url": "https://www.donga.com/news/Society/article/all/20260502/133850529/1",
    "date": "2026-05-02",
    "category": "사회",
    "source": "동아일보",
    "image_url": "https://dimg.donga.com/wps/NEWS/IMAGE/2026/05/02/133850530.1.jpg",
    "scraped_at": "2026-05-02T09:52:36.843301+09:00",
    "main_category": "사회"
  },
  {
    "title": "‘황금연휴 둘째날’ 토요일 교통량 증가…서울→부산 7시간",
    "url": "https://www.donga.com/news/Society/article/all/20260502/133850510/1",
    "date": "2026-05-02",
    "category": "사회",
    "source": "동아일보",
    "image_url": "https://dimg.donga.com/wps/NEWS/IMAGE/2026/05/02/133850511.1.jpg",
    "scraped_at": "2026-05-02T09:52:36.843379+09:00",
    "main_category": "사회"
  },
  {
    "title": "시속 50㎞ 도로서 153㎞ ‘광란의 추월’…승객 사망사고 낸 60대 택시기사",
    "url": "https://www.donga.com/news/Society/article/all/20260502/133850465/1",
    "date": "2026-05-02",
    "category": "사회",
    "source": "동아일보",
    "image_url": "https://dimg.donga.com/wps/NEWS/IMAGE/2026/05/02/133850466.1.jpg",
    "scraped_at": "2026-05-02T09:52:36.843444+09:00",
    "main_category": "사회"
  },
  {
    "title": "‘4월 이미 29도’ 대구보다 더 덥다…올여름도 ‘광프리카’ 예고",
    "url": "https://www.donga.com/news/Society/article/all/20260502/133850452/1",
    "date": "2026-05-02",
    "category": "사회",
    "source": "동아일보",
    "image_url": "https://dimg.donga.com/wps/NEWS/IMAGE/2026/05/02/133850453.1.jpg",
    "scraped_at": "2026-05-02T09:52:36.843603+09:00",
    "main_category": "사회"
  },
  {
    "title": "황영기 “아이들이 너무 일찍 어른 된다”…어린이날 앞둔 현실 [함께미래 리더스]",
    "url": "https://www.donga.com/news/Society/article/all/20260430/133820624/2",
    "date": "2026-04-30",
    "category": "사회",
    "source": "동아일보",
    "image_url": "https://dimg.donga.com/wps/NEWS/IMAGE/2026/04/30/133824215.3.jpg",
    "scraped_at": "2026-05-02T09:52:36.843534+09:00",
    "main_category": "사회"
  }
]