[
  {
    "title": "서해 피격 공무원 유족, 北 상대 승소한 日 강제북송 피해자 유족 만나",
    "url": "https://www.donga.com/news/Society/article/all/20260127/133238985/1",
    "date": "2026-01-27",
    "category": "사회",
    "source": "동아일보",
    "image_url": "https://dimg.donga.com/wps/NEWS/IMAGE/2026/01/27/133239311.1.png",
    "scraped_at": "2026-01-27T15:08:26.819186+09:00",
    "main_category": "사회"
  },
  {
    "title": "복통·설사 2~3주, 장염 아닙니다…젊은 환자 늘어난 이 질병",
    "url": "https://www.donga.com/news/Society/article/all/20260127/133239940/1",
    "date": "2026-01-27",
    "category": "사회",
    "source": "동아일보",
    "image_url": "https://dimg.donga.com/wps/NEWS/IMAGE/2026/01/27/133239941.1.jpg",
    "scraped_at": "2026-01-27T15:08:26.819265+09:00",
    "main_category": "사회"
  },
  {
    "title": "70세 이상 운전자, 면허반납시 최대 68만원 교통카드 지원",
    "url": "https://www.donga.com/news/Society/article/all/20260127/133239555/1",
    "date": "2026-01-27",
    "category": "사회",
    "source": "동아일보",
    "image_url": "https://dimg.donga.com/wps/NEWS/IMAGE/2026/01/27/133239834.1.jpg",
    "scraped_at": "2026-01-27T15:08:26.819331+09:00",
    "main_category": "사회"
  },
  {
    "title": "생활비 아껴 모은 292만원…쪽방 주민들이 보여준 ‘나눔의 역설’",
    "url": "https://www.donga.com/news/Society/article/all/20260127/133239787/2",
    "date": "2026-01-27",
    "category": "사회",
    "source": "동아일보",
    "image_url": "https://dimg.donga.com/wps/NEWS/IMAGE/2026/01/27/133239813.3.jpg",
    "scraped_at": "2026-01-27T15:08:26.819400+09:00",
    "main_category": "사회"
  },
  {
    "title": "경기 광명시, 50대 시민에 평생학습지원금 30만 원 지급",
    "url": "https://www.donga.com/news/Society/article/all/20260127/133239213/1",
    "date": "2026-01-27",
    "category": "사회",
    "source": "동아일보",
    "image_url": "https://dimg.donga.com/wps/NEWS/IMAGE/2026/01/27/133239258.1.jpg",
    "scraped_at": "2026-01-27T15:08:26.819463+09:00",
    "main_category": "사회"
  }
]