[
  {
    "title": "“옆집에서 시체 썩는 냄새가”…경찰 출동하게 만든 악취의 정체",
    "url": "https://www.donga.com/news/Inter/article/all/20260722/134343154/2",
    "date": "2026-07-22",
    "category": "국제",
    "source": "동아일보",
    "image_url": "https://dimg.donga.com/wps/NEWS/IMAGE/2026/07/22/134343256.3.png",
    "scraped_at": "2026-07-22T15:54:40.677698+09:00",
    "main_category": "국제"
  },
  {
    "title": "캐나다, 英·伊·日 차세대 전투기 개발사업에 옵서버 참여",
    "url": "https://www.donga.com/news/Inter/article/all/20260722/134343349/1",
    "date": "2026-07-22",
    "category": "국제",
    "source": "동아일보",
    "image_url": "https://dimg.donga.com/wps/NEWS/IMAGE/2026/07/22/134343538.1.jpg",
    "scraped_at": "2026-07-22T15:54:40.677773+09:00",
    "main_category": "국제"
  },
  {
    "title": "후티 ‘봉쇄’ 경고에 홍해 입구서 유조선 회항 잇달아",
    "url": "https://www.donga.com/news/Inter/article/all/20260722/134343247/1",
    "date": "2026-07-22",
    "category": "국제",
    "source": "동아일보",
    "image_url": "https://dimg.donga.com/wps/NEWS/IMAGE/2026/07/22/134343380.1.jpg",
    "scraped_at": "2026-07-22T15:54:40.677855+09:00",
    "main_category": "국제"
  },
  {
    "title": "“부모와 연 끊으세요”…상담실까지 번진 ‘가족 절연’ 논쟁",
    "url": "https://www.donga.com/news/Inter/article/all/20260722/134342762/2",
    "date": "2026-07-22",
    "category": "국제",
    "source": "동아일보",
    "image_url": "https://dimg.donga.com/wps/NEWS/IMAGE/2026/07/22/134343307.3.jpg",
    "scraped_at": "2026-07-22T15:54:40.677928+09:00",
    "main_category": "국제"
  },
  {
    "title": "日 체감 40도 폭염에 ‘인간 냉장고’ 나왔다…몇분만에 15도로 뚝",
    "url": "https://www.donga.com/news/Inter/article/all/20260722/134342676/2",
    "date": "2026-07-22",
    "category": "국제",
    "source": "동아일보",
    "image_url": "https://dimg.donga.com/wps/NEWS/IMAGE/2026/07/22/134344552.1.jpg",
    "scraped_at": "2026-07-22T15:54:40.677992+09:00",
    "main_category": "국제"
  }
]