[
  {
    "title": "“속옷까지 꼭 벗어야 돼요?”…日학교 건강검진 방식 두고 논란",
    "url": "https://www.donga.com/news/Inter/article/all/20260708/134261737/2",
    "date": "2026-07-08",
    "category": "국제",
    "source": "동아일보",
    "image_url": "https://dimg.donga.com/wps/NEWS/IMAGE/2026/07/08/134261772.3.jpg",
    "scraped_at": "2026-07-08T19:46:19.724395+09:00",
    "main_category": "국제"
  },
  {
    "title": "트럼프 “종전 MOU 끝났다…이란, 쓰레기이자 거짓말쟁이”",
    "url": "https://www.donga.com/news/Inter/article/all/20260708/134261755/2",
    "date": "2026-07-08",
    "category": "국제",
    "source": "동아일보",
    "image_url": "https://dimg.donga.com/wps/NEWS/IMAGE/2026/07/08/134261756.2.jpg",
    "scraped_at": "2026-07-08T19:46:19.724475+09:00",
    "main_category": "국제"
  },
  {
    "title": "월드컵이 美 대선 넘었다…폴리마켓 예측 거래액 6조 ‘사상 최대’",
    "url": "https://www.donga.com/news/Inter/article/all/20260708/134261670/1",
    "date": "2026-07-08",
    "category": "국제",
    "source": "동아일보",
    "image_url": "https://dimg.donga.com/wps/NEWS/IMAGE/2026/07/08/134261671.1.jpg",
    "scraped_at": "2026-07-08T19:46:19.724541+09:00",
    "main_category": "국제"
  },
  {
    "title": "트럼프 정부가 막았던 오픈AI 최상위 모델, 9일 풀린다",
    "url": "https://www.donga.com/news/Inter/article/all/20260708/134260952/1",
    "date": "2026-07-08",
    "category": "국제",
    "source": "동아일보",
    "image_url": "https://dimg.donga.com/wps/NEWS/IMAGE/2026/07/08/134260953.1.jpg",
    "scraped_at": "2026-07-08T19:46:19.724609+09:00",
    "main_category": "국제"
  },
  {
    "title": "사우디, UAE로 송금 차단…OPEC 탈퇴 보복 조치",
    "url": "https://www.donga.com/news/Inter/article/all/20260708/134259042/1",
    "date": "2026-07-08",
    "category": "국제",
    "source": "동아일보",
    "image_url": "https://dimg.donga.com/wps/NEWS/IMAGE/2026/05/27/134002524.1.jpg",
    "scraped_at": "2026-07-08T19:46:19.724670+09:00",
    "main_category": "국제"
  }
]