[
  {
    "title": "미얀마 군부독재 정부군, 서부 소수계 병원 폭격…“34명 사망”",
    "url": "https://www.donga.com/news/Inter/article/all/20251211/132950292/1",
    "date": "2025-12-11",
    "category": "국제",
    "source": "동아일보",
    "image_url": "https://dimg.donga.com/wps/NEWS/IMAGE/2025/12/11/132950293.1.jpg",
    "scraped_at": "2025-12-11T19:11:44.409832+09:00",
    "main_category": "국제"
  },
  {
    "title": "美, 베네수엘라 유조선 나포…트럼프 “이란 원유 밀수에 동원”",
    "url": "https://www.donga.com/news/Inter/article/all/20251211/132945583/1",
    "date": "2025-12-11",
    "category": "국제",
    "source": "동아일보",
    "image_url": "https://dimg.donga.com/wps/NEWS/IMAGE/2025/12/11/132945762.1.jpg",
    "scraped_at": "2025-12-11T19:11:44.409909+09:00",
    "main_category": "국제"
  },
  {
    "title": "대만 총통, 韓입국신고서 ‘중국(대만)’ 표기 항의…“우리에게 상처”",
    "url": "https://www.donga.com/news/Inter/article/all/20251211/132947889/2",
    "date": "2025-12-11",
    "category": "국제",
    "source": "동아일보",
    "image_url": "https://dimg.donga.com/wps/NEWS/IMAGE/2025/12/11/132947872.3.jpg",
    "scraped_at": "2025-12-11T19:11:44.409988+09:00",
    "main_category": "국제"
  },
  {
    "title": "마차도 “나를 위해 많은 사람 목숨 걸어…베네수엘라로 돌아갈 것”",
    "url": "https://www.donga.com/news/Inter/article/all/20251211/132947378/1",
    "date": "2025-12-11",
    "category": "국제",
    "source": "동아일보",
    "image_url": "https://dimg.donga.com/wps/NEWS/IMAGE/2025/12/11/132948333.1.jpg",
    "scraped_at": "2025-12-11T19:11:44.410056+09:00",
    "main_category": "국제"
  },
  {
    "title": "“中딥시크, 엔비디아칩 제3국 통해 밀반입… 새 AI모델 개발에 사용”",
    "url": "https://www.donga.com/news/Inter/article/all/20251211/132947351/1",
    "date": "2025-12-11",
    "category": "국제",
    "source": "동아일보",
    "image_url": "https://dimg.donga.com/wps/NEWS/IMAGE/2025/12/11/132948144.1.jpg",
    "scraped_at": "2025-12-11T19:11:44.410119+09:00",
    "main_category": "국제"
  }
]