[
  {
    "title": "[속보]내달부터 사상 첫 농지 전수조사…투기 뿌리 뽑는다",
    "url": "https://www.donga.com/news/Economy/article/all/20260401/133651417/2",
    "date": "2026-04-01",
    "category": "경제",
    "source": "동아일보",
    "scraped_at": "2026-04-01T09:47:14.252570+09:00",
    "main_category": "경제",
    "image_url": "https://dimg.donga.com/wps/NEWS/IMAGE/2026/04/01/133651426.3.jpg"
  },
  {
    "title": "[속보]코스피 급등에 매수 사이드카 발동",
    "url": "https://www.donga.com/news/Economy/article/all/20260401/133651360/2",
    "date": "2026-04-01",
    "category": "경제",
    "source": "동아일보",
    "scraped_at": "2026-04-01T09:47:14.252598+09:00",
    "main_category": "경제",
    "image_url": "https://dimg.donga.com/wps/NEWS/IMAGE/2026/04/01/133651559.1.jpg"
  },
  {
    "title": "[속보] 코스피 급등에 매수 사이드카 발동",
    "url": "https://www.donga.com/news/Economy/article/all/20260401/133651307/1",
    "date": "2026-04-01",
    "category": "경제",
    "source": "동아일보",
    "scraped_at": "2026-04-01T09:47:14.252612+09:00",
    "main_category": "경제",
    "image_url": "https://dimg.donga.com/wps/NEWS/IMAGE/2026/04/01/133651562.1.jpg"
  },
  {
    "title": "3월 수출 48.3%↑…사상 처음 月 800억 달러 넘어",
    "url": "https://www.donga.com/news/Economy/article/all/20260401/133651281/1",
    "date": "2026-04-01",
    "category": "경제",
    "source": "동아일보",
    "scraped_at": "2026-04-01T09:47:14.252630+09:00",
    "main_category": "경제",
    "image_url": "https://dimg.donga.com/wps/NEWS/IMAGE/2026/04/01/133651282.1.jpg"
  },
  {
    "title": "국내 첫 아사히 브랜드 RTD 제품, ‘아사히 클리어 하이볼’ 오는 8일 출시",
    "url": "https://www.donga.com/news/Economy/article/all/20260331/133646040/1",
    "date": "2026-03-31",
    "category": "경제",
    "source": "동아일보",
    "scraped_at": "2026-04-01T09:47:14.252644+09:00",
    "main_category": "경제",
    "image_url": "https://dimg.donga.com/wps/NEWS/IMAGE/2026/03/31/133645914.2.png"
  }
]