[
  {
    "title": "신현송 한은 총재, 취임 후 업무파악 집중…첫 출장은 BIS 총재회의",
    "url": "https://www.donga.com/news/Economy/article/all/20260428/133824548/1",
    "date": "2026-04-28",
    "category": "경제",
    "source": "동아일보",
    "scraped_at": "2026-04-28T09:52:57.951294+09:00",
    "main_category": "경제",
    "image_url": "https://dimg.donga.com/wps/NEWS/IMAGE/2026/04/28/133824549.1.jpg"
  },
  {
    "title": "‘초유케이크로 행복을 나누는 하루’ …뉴이미지 코리아, 해오름빌과 가족참여형 사회공헌활동 진행",
    "url": "https://www.donga.com/news/Economy/article/all/20260428/133824530/1",
    "date": "2026-04-28",
    "category": "경제",
    "source": "동아일보",
    "scraped_at": "2026-04-28T09:52:57.951318+09:00",
    "main_category": "경제",
    "image_url": "https://dimg.donga.com/wps/NEWS/IMAGE/2026/04/28/133824435.2.png"
  },
  {
    "title": "‘고환율의 역설’ 한은 1분기 순이익 4.2조 ‘역대 최대’…작년의 3배",
    "url": "https://www.donga.com/news/Economy/article/all/20260428/133824511/1",
    "date": "2026-04-28",
    "category": "경제",
    "source": "동아일보",
    "scraped_at": "2026-04-28T09:52:57.951334+09:00",
    "main_category": "경제",
    "image_url": "https://dimg.donga.com/wps/NEWS/IMAGE/2026/04/28/133824512.1.jpg"
  },
  {
    "title": "코스피, 6670 찍었다…또 사상 최고치",
    "url": "https://www.donga.com/news/Economy/article/all/20260428/133824322/1",
    "date": "2026-04-28",
    "category": "경제",
    "source": "동아일보",
    "scraped_at": "2026-04-28T09:52:57.951351+09:00",
    "main_category": "경제",
    "image_url": "https://dimg.donga.com/wps/NEWS/IMAGE/2026/04/28/133824323.1.jpg"
  },
  {
    "title": "대우건설, 깜짝 실적…1분기 영업익 2556억원 전년비 69% ↑",
    "url": "https://www.donga.com/news/Economy/article/all/20260428/133824118/1",
    "date": "2026-04-28",
    "category": "경제",
    "source": "동아일보",
    "scraped_at": "2026-04-28T09:52:57.951364+09:00",
    "main_category": "경제",
    "image_url": "https://dimg.donga.com/wps/NEWS/IMAGE/2026/04/28/133824119.1.jpg"
  }
]