[
  {
    "title": "李 \"부동산 정상화? 5000피보다 쉬워…마지막 기회 잡으시길\"",
    "url": "https://www.joongang.co.kr/article/25401723",
    "date": "2026-01-31",
    "category": "정치",
    "source": "중앙일보",
    "image_url": "https://pds.joongang.co.kr/news/FbMetaImage/202601/1ef2ee81-a9f0-48a2-a729-d73feccd45e4.png",
    "scraped_at": "2026-01-31T15:09:02.283154+09:00",
    "main_category": "정치"
  },
  {
    "title": "이해찬 울린 '38년 맞수'도 찾았다…마지막 길 배웅 온 野인사들",
    "url": "https://www.joongang.co.kr/article/25401733",
    "date": "2026-01-31",
    "category": "정치",
    "source": "중앙일보",
    "image_url": "https://pds.joongang.co.kr/news/component/htmlphoto_mmdata/202601/31/4d9e8c5a-e95f-447f-98e5-2d95a93cf98b.jpg",
    "scraped_at": "2026-01-31T15:09:02.283342+09:00",
    "main_category": "정치"
  },
  {
    "title": "\"오세훈 이럴 줄 꿈에도 몰라\"…장동혁 퇴진 요구 '급발진' 왜",
    "url": "https://www.joongang.co.kr/article/25401619",
    "date": "2026-01-31",
    "category": "정치",
    "source": "중앙일보",
    "image_url": "https://pds.joongang.co.kr/news/FbMetaImage/202601/c7e52c47-25a6-438b-8169-0f66067a585a.png",
    "scraped_at": "2026-01-31T15:09:02.283563+09:00",
    "main_category": "정치"
  },
  {
    "title": "트럼프 '기습 관세' 쿠팡 탓?…한미관계 돌변하는 '기폭제' 있었다",
    "url": "https://www.joongang.co.kr/article/25401721",
    "date": "2026-01-31",
    "category": "정치",
    "source": "중앙일보",
    "image_url": "https://pds.joongang.co.kr/news/component/htmlphoto_mmdata/202601/31/bd996992-7298-42ff-882d-f82c3a66958c.jpg",
    "scraped_at": "2026-01-31T15:09:02.283792+09:00",
    "main_category": "정치"
  },
  {
    "title": "[속보] 공군 수송기 엔진 결함으로 日나하기지 비상착륙",
    "url": "https://www.joongang.co.kr/article/25401591",
    "date": "2026-01-31",
    "category": "정치",
    "source": "중앙일보",
    "image_url": "",
    "scraped_at": "2026-01-31T15:09:02.284044+09:00",
    "main_category": "정치"
  }
]