[
  {
    "title": "거짓말처럼 같은 해 세상 떠난 두 절친배우가 남긴 명작영화",
    "url": "https://www.joongang.co.kr/article/25417260",
    "date": "2026-04-04",
    "category": "문화",
    "source": "중앙일보",
    "image_url": "https://pds.joongang.co.kr/news/component/htmlphoto_mmdata/202604/03/ed8e1da7-3d1e-4384-a4dc-f33821f9d1d9.jpg",
    "scraped_at": "2026-04-04T19:15:01.635956+09:00",
    "main_category": "문화"
  },
  {
    "title": "“파리바게뜨서 김치 먹는 느낌” BTS도 이해못한 방시혁 속내",
    "url": "https://www.joongang.co.kr/article/25417471",
    "date": "2026-04-04",
    "category": "문화",
    "source": "중앙일보",
    "image_url": "https://pds.joongang.co.kr/news/FbMetaImage/202604/983eac93-2a1d-47c6-8c9e-4dbebcc93d0e.jpg",
    "scraped_at": "2026-04-04T19:15:01.636139+09:00",
    "main_category": "문화"
  },
  {
    "title": "“엄마랑 똑같이 생겼네”…K팝 뮤비 깜짝 등장한 ‘졸리 딸’ 무슨 일",
    "url": "https://www.joongang.co.kr/article/25417507",
    "date": "2026-04-04",
    "category": "문화",
    "source": "중앙일보",
    "image_url": "https://pds.joongang.co.kr/news/FbMetaImage/202604/5d489f06-d457-4589-a157-36e570044fbb.jpg",
    "scraped_at": "2026-04-04T19:15:01.636381+09:00",
    "main_category": "문화"
  },
  {
    "title": "까맣게 탄 얼굴에 군기 바짝…해병대 간 정동원 ‘깜짝 근황’",
    "url": "https://www.joongang.co.kr/article/25417368",
    "date": "2026-04-04",
    "category": "문화",
    "source": "중앙일보",
    "image_url": "https://pds.joongang.co.kr/news/FbMetaImage/202604/e0588b32-3b80-4075-bf88-0241f729229b.jpg",
    "scraped_at": "2026-04-04T19:15:01.636609+09:00",
    "main_category": "문화"
  },
  {
    "title": "“그때 샀더라면”…후회를 부르는 돈, 도대체 무엇이길래[BOOK]",
    "url": "https://www.joongang.co.kr/article/25417294",
    "date": "2026-04-04",
    "category": "문화",
    "source": "중앙일보",
    "image_url": "",
    "scraped_at": "2026-04-04T19:15:01.636858+09:00",
    "main_category": "문화"
  }
]