[
  {
    "title": "BTS 앨범, 첫 트랙부터 ‘아리랑’ 등장…“방시혁 의장 아이디어” [BTS 컴백]",
    "url": "https://www.joongang.co.kr/article/25413465",
    "date": "2026-03-21",
    "category": "문화",
    "source": "중앙일보",
    "image_url": "https://pds.joongang.co.kr/news/component/htmlphoto_mmdata/202603/20/b56ab9ce-a455-4aa8-9622-b611d43415e4.jpg",
    "scraped_at": "2026-03-21T19:10:43.726313+09:00",
    "main_category": "문화"
  },
  {
    "title": "“쎄하네” 2시간이면 다 안다, 뒤통수 때리는 배신자 특징 7",
    "url": "https://www.joongang.co.kr/article/25413315",
    "date": "2026-03-21",
    "category": "문화",
    "source": "중앙일보",
    "image_url": "https://pds.joongang.co.kr/news/component/htmlphoto_mmdata/202603/20/4e83cf40-1ba0-4232-a814-86fd3ee3e7a4.jpg",
    "scraped_at": "2026-03-21T19:10:43.726513+09:00",
    "main_category": "문화"
  },
  {
    "title": "BTS \"살면서 광화문 공연은 상상도 못 해…아리랑 합창 기대돼\"",
    "url": "https://www.joongang.co.kr/article/25413640",
    "date": "2026-03-21",
    "category": "문화",
    "source": "중앙일보",
    "image_url": "https://pds.joongang.co.kr/news/FbMetaImage/202603/38736acf-31d7-40fc-9366-97e33dcf228c.jpg",
    "scraped_at": "2026-03-21T19:10:43.726713+09:00",
    "main_category": "문화"
  },
  {
    "title": "BTS 7인 얼굴 분석해보니…\"왕제비상\" 인상학자 놀란 멤버",
    "url": "https://www.joongang.co.kr/article/25413307",
    "date": "2026-03-21",
    "category": "문화",
    "source": "중앙일보",
    "image_url": "https://pds.joongang.co.kr/news/FbMetaImage/202603/cd55fa35-8302-4c59-b112-5423b6344a07.jpg",
    "scraped_at": "2026-03-21T19:10:43.726933+09:00",
    "main_category": "문화"
  },
  {
    "title": "BTS ‘왕의 문’으로 나오나…‘군주급 컴백’ 이뤄지는 광화문 월대 어떤 곳 [BTS 컴백]",
    "url": "https://www.joongang.co.kr/article/25413611",
    "date": "2026-03-21",
    "category": "문화",
    "source": "중앙일보",
    "image_url": "https://pds.joongang.co.kr/news/component/htmlphoto_mmdata/202603/21/17736080-1c3f-4962-96f6-b5ad5b6f36d9.jpg",
    "scraped_at": "2026-03-21T19:10:43.727185+09:00",
    "main_category": "문화"
  }
]