[
  {
    "title": "“성 바꿔 활동”…훈남 배우 최상엽, 박미선·이봉원 아들이었다",
    "url": "https://www.joongang.co.kr/article/25441664",
    "date": "2026-07-02",
    "category": "문화",
    "source": "중앙일보",
    "image_url": "https://pds.joongang.co.kr/news/component/htmlphoto_mmdata/202607/02/fd0c713e-c5f4-4a3f-94bd-2963df5e4242.jpg",
    "scraped_at": "2026-07-02T10:02:20.887217+09:00",
    "main_category": "문화"
  },
  {
    "title": "유관순 열사를 “관순이” 불렀다…이화를 만든 140년전 그 딸들",
    "url": "https://www.joongang.co.kr/article/25440775",
    "date": "2026-07-02",
    "category": "문화",
    "source": "중앙일보",
    "image_url": "https://pds.joongang.co.kr/news/component/htmlphoto_mmdata/202606/29/227e787b-2dcf-40fd-865a-22d1f411735e.jpg",
    "scraped_at": "2026-07-02T10:02:20.887384+09:00",
    "main_category": "문화"
  },
  {
    "title": "‘어우동’ 상영 중 필름 압수…관객이 끝내 보지못한 그 장면 정체",
    "url": "https://www.joongang.co.kr/article/25440972",
    "date": "2026-07-02",
    "category": "문화",
    "source": "중앙일보",
    "image_url": "https://pds.joongang.co.kr/news/FbMetaImage/202606/f1a461f3-0b03-4a31-8388-dab3a253790c.jpg",
    "scraped_at": "2026-07-02T10:02:20.887557+09:00",
    "main_category": "문화"
  },
  {
    "title": "‘사탄과 섹스’ 더러운 피 끊는다…통일교 신자 집엔 꼭 있는 것",
    "url": "https://www.joongang.co.kr/article/25439808",
    "date": "2026-07-02",
    "category": "문화",
    "source": "중앙일보",
    "image_url": "https://pds.joongang.co.kr/news/component/htmlphoto_mmdata/202606/25/48184926-28ed-400d-969d-5dd775b2dfe9.jpg",
    "scraped_at": "2026-07-02T10:02:20.887772+09:00",
    "main_category": "문화"
  },
  {
    "title": "책방골목 순례하는 배우…“책은 타인의 삶 살게한다”",
    "url": "https://www.joongang.co.kr/article/25441347",
    "date": "2026-07-02",
    "category": "문화",
    "source": "중앙일보",
    "image_url": "https://pds.joongang.co.kr/news/component/htmlphoto_mmdata/202607/01/765d5266-619c-48e4-b9dc-8e12d04e06b9.jpg",
    "scraped_at": "2026-07-02T10:02:20.887993+09:00",
    "main_category": "문화"
  }
]