[
  {
    "title": "‘MLB 도전’ 송성문, 옆구리 부상 4주 진단…WBC 출전 불투명",
    "url": "https://www.donga.com/news/Sports/article/all/20260117/133176545/1",
    "date": "2026-01-17",
    "category": "스포츠",
    "source": "동아일보",
    "image_url": "https://dimg.donga.com/wps/NEWS/IMAGE/2026/01/17/133176546.1.jpg",
    "scraped_at": "2026-01-17T19:06:50.067011+09:00",
    "main_category": "스포츠"
  },
  {
    "title": "김성현, PGA 투어 개막전 2R 공동 선두…“주말 라운드 기대돼”",
    "url": "https://www.donga.com/news/Sports/article/all/20260117/133176459/1",
    "date": "2026-01-17",
    "category": "스포츠",
    "source": "동아일보",
    "image_url": "https://dimg.donga.com/wps/NEWS/IMAGE/2026/01/17/133176591.1.jpg",
    "scraped_at": "2026-01-17T19:06:50.067090+09:00",
    "main_category": "스포츠"
  },
  {
    "title": "‘U-23 아시안컵 준결승행’ 김상식 베트남 감독 “한계 극복하겠다”",
    "url": "https://www.donga.com/news/Sports/article/all/20260117/133176452/1",
    "date": "2026-01-17",
    "category": "스포츠",
    "source": "동아일보",
    "image_url": "https://dimg.donga.com/wps/NEWS/IMAGE/2026/01/17/133176453.1.jpg",
    "scraped_at": "2026-01-17T19:06:50.067157+09:00",
    "main_category": "스포츠"
  },
  {
    "title": "호주전 앞둔 이민성 감독 “하늘이 준 기회…하나로 뭉쳐 승리하겠다”",
    "url": "https://www.donga.com/news/Sports/article/all/20260117/133176370/1",
    "date": "2026-01-17",
    "category": "스포츠",
    "source": "동아일보",
    "image_url": "https://dimg.donga.com/wps/NEWS/IMAGE/2026/01/17/133176371.1.jpg",
    "scraped_at": "2026-01-17T19:06:50.067228+09:00",
    "main_category": "스포츠"
  },
  {
    "title": "‘연패 탈출’ 현대건설 양효진 “어느 때보다 치열한 시즌…집중력이 중요”",
    "url": "https://www.donga.com/news/Sports/article/all/20260117/133176260/1",
    "date": "2026-01-17",
    "category": "스포츠",
    "source": "동아일보",
    "image_url": "https://dimg.donga.com/wps/NEWS/IMAGE/2026/01/17/133176261.1.jpg",
    "scraped_at": "2026-01-17T19:06:50.067292+09:00",
    "main_category": "스포츠"
  }
]