[
  {
    "title": "“韓 컬링 최초 금메달리스트가 되겠다”…‘금빛 스위핑’ 시작하는 여자 컬링",
    "url": "https://www.donga.com/news/Sports/article/all/20260211/133344879/1",
    "date": "2026-02-11",
    "category": "스포츠",
    "source": "동아일보",
    "image_url": "https://dimg.donga.com/wps/NEWS/IMAGE/2026/01/27/133239009.1.jpg",
    "scraped_at": "2026-02-11T15:24:15.338783+09:00",
    "main_category": "스포츠"
  },
  {
    "title": "프로농구 삼성 김효범 감독, 경기 지각 논란으로 재정위 회부",
    "url": "https://www.donga.com/news/Sports/article/all/20260211/133344409/1",
    "date": "2026-02-11",
    "category": "스포츠",
    "source": "동아일보",
    "image_url": "https://dimg.donga.com/wps/NEWS/IMAGE/2026/02/11/133344410.1.jpg",
    "scraped_at": "2026-02-11T15:24:15.338863+09:00",
    "main_category": "스포츠"
  },
  {
    "title": "“여친 두고 바람피웠다”…노르웨이 메달리스트 황당 인터뷰",
    "url": "https://www.donga.com/news/Sports/article/all/20260211/133343594/2",
    "date": "2026-02-11",
    "category": "스포츠",
    "source": "동아일보",
    "image_url": "https://dimg.donga.com/wps/NEWS/IMAGE/2026/02/11/133343587.3.jpg",
    "scraped_at": "2026-02-11T15:24:15.338927+09:00",
    "main_category": "스포츠"
  },
  {
    "title": "스케이트 날에 목 베인 사고 딛고…‘두 번째 올림픽’ 출전한 호주 선수",
    "url": "https://www.donga.com/news/Sports/article/all/20260211/133343892/1",
    "date": "2026-02-11",
    "category": "스포츠",
    "source": "동아일보",
    "image_url": "https://dimg.donga.com/wps/NEWS/IMAGE/2026/02/11/133343893.1.jpg",
    "scraped_at": "2026-02-11T15:24:15.338995+09:00",
    "main_category": "스포츠"
  },
  {
    "title": "우크라 선수, IOC 제동에도 불복…“추모 헬멧 쓸 것”",
    "url": "https://www.donga.com/news/Sports/article/all/20260211/133342436/1",
    "date": "2026-02-11",
    "category": "스포츠",
    "source": "동아일보",
    "image_url": "https://dimg.donga.com/wps/NEWS/IMAGE/2026/02/11/133338063.4.jpg",
    "scraped_at": "2026-02-11T15:24:15.339075+09:00",
    "main_category": "스포츠"
  }
]