[
  {
    "title": "\"어린이집 교사 너무 화나\"…영하 8도에 아이들과 두쫀쿠 오픈런",
    "url": "https://www.joongang.co.kr/article/25396562",
    "date": "2026-01-11",
    "category": "사회",
    "source": "중앙일보",
    "image_url": "https://pds.joongang.co.kr/news/component/htmlphoto_mmdata/202601/10/870a25e4-f174-4b76-b835-f829e4c1668d.jpg",
    "scraped_at": "2026-01-11T09:36:00.591000+09:00",
    "main_category": "사회"
  },
  {
    "title": "고모부가 데려다준 고시원…20살 소녀 방은 연기가 났다",
    "url": "https://www.joongang.co.kr/article/25396515",
    "date": "2026-01-11",
    "category": "사회",
    "source": "중앙일보",
    "image_url": "https://pds.joongang.co.kr/news/FbMetaImage/202601/c79bb183-0a7e-40c0-8dad-89030dfd8d4d.png",
    "scraped_at": "2026-01-11T09:36:00.591186+09:00",
    "main_category": "사회"
  },
  {
    "title": "사고로 장기 적출한 배달기사…'월 700만원' 최고 직업 찾다",
    "url": "https://www.joongang.co.kr/article/25396577",
    "date": "2026-01-11",
    "category": "사회",
    "source": "중앙일보",
    "image_url": "https://pds.joongang.co.kr/news/component/htmlphoto_mmdata/202601/11/2d4da8e9-efc6-460f-8e23-d7dc4ae3a93f.jpg",
    "scraped_at": "2026-01-11T09:36:00.591382+09:00",
    "main_category": "사회"
  },
  {
    "title": "'사생활 논란' 입 연 정희원 \"부적절한 처신…멈추지 못 했다\"",
    "url": "https://www.joongang.co.kr/article/25396567",
    "date": "2026-01-11",
    "category": "사회",
    "source": "중앙일보",
    "image_url": "https://pds.joongang.co.kr/news/component/htmlphoto_mmdata/202601/11/edc7e83b-b2a3-4e6c-af6b-fedc53d28cce.jpg",
    "scraped_at": "2026-01-11T09:36:00.591603+09:00",
    "main_category": "사회"
  },
  {
    "title": "돈으로 못 산다더니…연봉 따라 수명 9년까지 차이난다, 왜",
    "url": "https://www.joongang.co.kr/article/25396510",
    "date": "2026-01-11",
    "category": "사회",
    "source": "중앙일보",
    "image_url": "",
    "scraped_at": "2026-01-11T09:36:00.591872+09:00",
    "main_category": "사회"
  }
]