[
  {
    "title": "군산 금강하굿둑 인근서 20대 남성 변사체 발견…실종 대학생 추정",
    "url": "https://www.donga.com/news/Society/article/all/20260301/133444125/1",
    "date": "2026-03-01",
    "category": "사회",
    "source": "동아일보",
    "image_url": "https://dimg.donga.com/wps/NEWS/IMAGE/2026/03/01/133444126.1.jpg",
    "scraped_at": "2026-03-01T19:10:09.974382+09:00",
    "main_category": "사회"
  },
  {
    "title": "정부, 내년부터 18세 청년에 국민연금 첫달 보험료 지원",
    "url": "https://www.donga.com/news/Society/article/all/20260301/133443178/1",
    "date": "2026-03-01",
    "category": "사회",
    "source": "동아일보",
    "image_url": "https://dimg.donga.com/wps/NEWS/IMAGE/2026/03/01/133444113.1.jpg",
    "scraped_at": "2026-03-01T19:10:09.974462+09:00",
    "main_category": "사회"
  },
  {
    "title": "‘사법 3법’ 통과 마무리…李정부서 대법관 26명 중 22명 임명 가능",
    "url": "https://www.donga.com/news/Society/article/all/20260301/133442835/1",
    "date": "2026-03-01",
    "category": "사회",
    "source": "동아일보",
    "image_url": "https://dimg.donga.com/wps/NEWS/IMAGE/2026/03/01/133444021.1.jpg",
    "scraped_at": "2026-03-01T19:10:09.974528+09:00",
    "main_category": "사회"
  },
  {
    "title": "서울숲 산책로서 자전거 타면 과태료 5만 원",
    "url": "https://www.donga.com/news/Society/article/all/20260301/133443083/1",
    "date": "2026-03-01",
    "category": "사회",
    "source": "동아일보",
    "image_url": "https://image.donga.com/pc/2022/images/common/donga_icon.jpg",
    "scraped_at": "2026-03-01T19:10:09.974588+09:00",
    "main_category": "사회"
  },
  {
    "title": "280억 원대 도박사이트 운영진, 전부 무죄…“경찰 위법한 증거 수집”",
    "url": "https://www.donga.com/news/Society/article/all/20260301/133443091/1",
    "date": "2026-03-01",
    "category": "사회",
    "source": "동아일보",
    "image_url": "https://dimg.donga.com/wps/NEWS/IMAGE/2026/03/01/133443367.1.jpg",
    "scraped_at": "2026-03-01T19:10:09.974656+09:00",
    "main_category": "사회"
  }
]