[
  {
    "title": "울산 전통시장서 문어 훔친 50대…“배고파서”",
    "url": "https://www.donga.com/news/Society/article/all/20260409/133704749/2",
    "date": "2026-04-09",
    "category": "사회",
    "source": "동아일보",
    "image_url": "https://dimg.donga.com/wps/NEWS/IMAGE/2026/04/09/133704753.3.jpg",
    "scraped_at": "2026-04-09T09:37:56.575033+09:00",
    "main_category": "사회"
  },
  {
    "title": "또래보다 작은아이, 성장호르몬 결핍이 원인",
    "url": "https://www.donga.com/news/Society/article/all/20260409/133682567/1",
    "date": "2026-04-09",
    "category": "사회",
    "source": "동아일보",
    "image_url": "https://dimg.donga.com/wps/NEWS/IMAGE/2026/04/09/133682580.1.jpg",
    "scraped_at": "2026-04-09T09:37:56.575140+09:00",
    "main_category": "사회"
  },
  {
    "title": "제주 강풍·호우특보…항공기 12편 결항",
    "url": "https://www.donga.com/news/Society/article/all/20260409/133704683/1",
    "date": "2026-04-09",
    "category": "사회",
    "source": "동아일보",
    "image_url": "https://dimg.donga.com/wps/NEWS/IMAGE/2026/04/09/133704684.1.jpg",
    "scraped_at": "2026-04-09T09:37:56.575208+09:00",
    "main_category": "사회"
  },
  {
    "title": "대전 중구서 ‘술에 취해 자기차에 불’…2600만원 피해",
    "url": "https://www.donga.com/news/Society/article/all/20260409/133704625/1",
    "date": "2026-04-09",
    "category": "사회",
    "source": "동아일보",
    "image_url": "https://dimg.donga.com/wps/NEWS/IMAGE/2026/04/09/133704626.1.jpg",
    "scraped_at": "2026-04-09T09:37:56.575276+09:00",
    "main_category": "사회"
  },
  {
    "title": "“늑구야 어딨니”…오월드 탈출 늑대, 250명 수색팀과 밤샘 숨바꼭질",
    "url": "https://www.donga.com/news/Society/article/all/20260409/133704523/1",
    "date": "2026-04-09",
    "category": "사회",
    "source": "동아일보",
    "image_url": "https://dimg.donga.com/wps/NEWS/IMAGE/2026/04/09/133704524.1.jpg",
    "scraped_at": "2026-04-09T09:37:56.575341+09:00",
    "main_category": "사회"
  }
]