[
  {
    "title": "유럽 망명 신청했는데 아프리카로?…EU ‘제3국 이송제도’ 승인",
    "url": "https://www.donga.com/news/Inter/article/all/20260211/133345265/1",
    "date": "2026-02-11",
    "category": "국제",
    "source": "동아일보",
    "image_url": "https://dimg.donga.com/wps/NEWS/IMAGE/2026/02/11/133345433.1.jpg",
    "scraped_at": "2026-02-11T15:27:10.911696+09:00",
    "main_category": "국제"
  },
  {
    "title": "日 홋카이도 해수욕장서 한국인 시체 발견…경찰 조사 중",
    "url": "https://www.donga.com/news/Inter/article/all/20260211/133345238/1",
    "date": "2026-02-11",
    "category": "국제",
    "source": "동아일보",
    "image_url": "https://dimg.donga.com/wps/NEWS/IMAGE/2026/02/11/133345239.1.jpg",
    "scraped_at": "2026-02-11T15:27:10.911775+09:00",
    "main_category": "국제"
  },
  {
    "title": "‘고수익 해외취업’ 속아 우크라 최전선에…케냐 외무, 러시아 방문 예정",
    "url": "https://www.donga.com/news/Inter/article/all/20260211/133344869/1",
    "date": "2026-02-11",
    "category": "국제",
    "source": "동아일보",
    "image_url": "https://dimg.donga.com/wps/NEWS/IMAGE/2026/02/11/133344870.1.jpg",
    "scraped_at": "2026-02-11T15:27:10.911843+09:00",
    "main_category": "국제"
  },
  {
    "title": "화요일 밤 9시면 학생들 술렁…美명문대 휩쓴 ‘데이트 드롭’ 정체는?",
    "url": "https://www.donga.com/news/Inter/article/all/20260211/133344172/1",
    "date": "2026-02-11",
    "category": "국제",
    "source": "동아일보",
    "image_url": "https://dimg.donga.com/wps/NEWS/IMAGE/2026/02/11/133344182.1.jpg",
    "scraped_at": "2026-02-11T15:27:10.911911+09:00",
    "main_category": "국제"
  },
  {
    "title": "日총선 표분석 해보니…‘청년·무당층 끌어안은 보수’는 강했다",
    "url": "https://www.donga.com/news/Inter/article/all/20260211/133344459/1",
    "date": "2026-02-11",
    "category": "국제",
    "source": "동아일보",
    "image_url": "https://dimg.donga.com/wps/NEWS/IMAGE/2026/02/11/133330747.1.jpg",
    "scraped_at": "2026-02-11T15:27:10.911974+09:00",
    "main_category": "국제"
  }
]