[
  {
    "title": "조용하던 멜라니아 달라졌다…아동법안·우크라·AI까지 직접 챙긴다",
    "url": "https://www.donga.com/news/Inter/article/all/20260707/134251977/1",
    "date": "2026-07-07",
    "category": "국제",
    "source": "동아일보",
    "image_url": "https://dimg.donga.com/wps/NEWS/IMAGE/2026/07/07/134251978.1.jpg",
    "scraped_at": "2026-07-07T16:11:46.426952+09:00",
    "main_category": "국제"
  },
  {
    "title": "‘암흑 천지’ 쿠바, 또 대정전…“1000만명 40도 무더위와 사투”",
    "url": "https://www.donga.com/news/Inter/article/all/20260707/134251095/1",
    "date": "2026-07-07",
    "category": "국제",
    "source": "동아일보",
    "image_url": "https://dimg.donga.com/wps/NEWS/IMAGE/2026/07/07/134251828.1.jpg",
    "scraped_at": "2026-07-07T16:11:46.427022+09:00",
    "main_category": "국제"
  },
  {
    "title": "트럼프 “시진핑, 9월 24일 방미 가능성… 백악관 대형 연회장 필요”",
    "url": "https://www.donga.com/news/Inter/article/all/20260707/134251553/1",
    "date": "2026-07-07",
    "category": "국제",
    "source": "동아일보",
    "image_url": "https://dimg.donga.com/wps/NEWS/IMAGE/2026/07/07/134251769.1.jpg",
    "scraped_at": "2026-07-07T16:11:46.427075+09:00",
    "main_category": "국제"
  },
  {
    "title": "사람 잡는 스페인 폭염…7월 초 150명 사망 추정, 산불도 확산",
    "url": "https://www.donga.com/news/Inter/article/all/20260707/134251656/1",
    "date": "2026-07-07",
    "category": "국제",
    "source": "동아일보",
    "image_url": "https://dimg.donga.com/wps/NEWS/IMAGE/2026/07/07/134251657.1.jpg",
    "scraped_at": "2026-07-07T16:11:46.427131+09:00",
    "main_category": "국제"
  },
  {
    "title": "中 SLBM 발사에 日 “안보 환경 더 심각해져…안보 3문서 개정에 속도”",
    "url": "https://www.donga.com/news/Inter/article/all/20260707/134251513/1",
    "date": "2026-07-07",
    "category": "국제",
    "source": "동아일보",
    "image_url": "https://dimg.donga.com/wps/NEWS/IMAGE/2026/07/07/134251514.1.jpg",
    "scraped_at": "2026-07-07T16:11:46.427180+09:00",
    "main_category": "국제"
  }
]