[
  {
    "title": "구두 선물에 빠진 트럼프…“사이즈 안맞아도 눈치보여 신는다”",
    "url": "https://www.donga.com/news/Inter/article/all/20260310/133499302/1",
    "date": "2026-03-10",
    "category": "국제",
    "source": "동아일보",
    "image_url": "https://dimg.donga.com/wps/NEWS/IMAGE/2026/03/10/133500435.1.jpg",
    "scraped_at": "2026-03-10T15:15:33.954377+09:00",
    "main_category": "국제"
  },
  {
    "title": "피파 “중동 전쟁에도 월드컵 연기는 불가…매일 상황 평가 중”",
    "url": "https://www.donga.com/news/Inter/article/all/20260310/133499735/1",
    "date": "2026-03-10",
    "category": "국제",
    "source": "동아일보",
    "image_url": "https://image.donga.com/pc/2022/images/common/donga_icon.jpg",
    "scraped_at": "2026-03-10T15:15:33.954446+09:00",
    "main_category": "국제"
  },
  {
    "title": "앤스로픽, 美정부 상대 소송…“견해 다르다고 위험기업 지정 위헌”",
    "url": "https://www.donga.com/news/Inter/article/all/20260310/133498995/1",
    "date": "2026-03-10",
    "category": "국제",
    "source": "동아일보",
    "image_url": "https://dimg.donga.com/wps/NEWS/IMAGE/2026/03/10/133499050.1.jpg",
    "scraped_at": "2026-03-10T15:15:33.954504+09:00",
    "main_category": "국제"
  },
  {
    "title": "이란 “美·이스라엘 외교관 추방하는 나라에 호르무즈 통행권 부여”",
    "url": "https://www.donga.com/news/Inter/article/all/20260310/133498904/1",
    "date": "2026-03-10",
    "category": "국제",
    "source": "동아일보",
    "image_url": "https://dimg.donga.com/wps/NEWS/IMAGE/2026/03/10/133498974.1.jpg",
    "scraped_at": "2026-03-10T15:15:33.954570+09:00",
    "main_category": "국제"
  },
  {
    "title": "노벨상 경제학자 “AI, 인간 노동 대규모 대체 어려워…거품 꺼지면 경제 충격”",
    "url": "https://www.donga.com/news/Inter/article/all/20260310/133498784/1",
    "date": "2026-03-10",
    "category": "국제",
    "source": "동아일보",
    "image_url": "https://dimg.donga.com/wps/NEWS/IMAGE/2026/03/10/133498785.1.jpg",
    "scraped_at": "2026-03-10T15:15:33.954633+09:00",
    "main_category": "국제"
  }
]