[
  {
    "title": "이창용 한은 총재 “국민연금 해외투자 너무 투명…불투명하게 할 필요”",
    "url": "https://www.donga.com/news/Economy/article/all/20251217/132985298/1",
    "date": "2025-12-17",
    "category": "경제",
    "source": "동아일보",
    "scraped_at": "2025-12-17T15:07:06.032116+09:00",
    "main_category": "경제",
    "image_url": "https://dimg.donga.com/wps/NEWS/IMAGE/2025/12/17/132985368.1.jpg"
  },
  {
    "title": "샤오미, 주요제품 연말 할인시작… 신기술 적용한 신기종 추가출시 예고",
    "url": "https://www.donga.com/news/Economy/article/all/20251217/132985325/1",
    "date": "2025-12-17",
    "category": "경제",
    "source": "동아일보",
    "scraped_at": "2025-12-17T15:07:06.032140+09:00",
    "main_category": "경제",
    "image_url": "https://dimg.donga.com/wps/NEWS/IMAGE/2025/12/17/132985281.2.jpg"
  },
  {
    "title": "환율, 장중 1480원 돌파…8개월 만에 최고",
    "url": "https://www.donga.com/news/Economy/article/all/20251217/132985014/2",
    "date": "2025-12-17",
    "category": "경제",
    "source": "동아일보",
    "scraped_at": "2025-12-17T15:07:06.032154+09:00",
    "main_category": "경제",
    "image_url": "https://dimg.donga.com/wps/NEWS/IMAGE/2025/12/17/132985015.2.jpg"
  },
  {
    "title": "원바이오젠, 구미시 삼성원에 보습 제품 · 기부금 후원",
    "url": "https://www.donga.com/news/Economy/article/all/20251217/132985010/1",
    "date": "2025-12-17",
    "category": "경제",
    "source": "동아일보",
    "scraped_at": "2025-12-17T15:07:06.032170+09:00",
    "main_category": "경제",
    "image_url": "https://dimg.donga.com/wps/NEWS/IMAGE/2025/12/17/132984973.2.jpg"
  },
  {
    "title": "제주삼다수, 자연이 만든 ‘31년’ 여정… 지하수 생성연령 첫 규명",
    "url": "https://www.donga.com/news/Economy/article/all/20251217/132984824/1",
    "date": "2025-12-17",
    "category": "경제",
    "source": "동아일보",
    "scraped_at": "2025-12-17T15:07:06.032183+09:00",
    "main_category": "경제",
    "image_url": "https://dimg.donga.com/wps/NEWS/IMAGE/2025/12/17/132984820.2.jpg"
  }
]